README.md
pyproject.toml
setup.py
amanzi/__init__.py
amanzi.egg-info/PKG-INFO
amanzi.egg-info/SOURCES.txt
amanzi.egg-info/dependency_links.txt
amanzi.egg-info/requires.txt
amanzi.egg-info/top_level.txt
amanzi.egg-info/zip-safe
amanzi/assets/__init__.py
amanzi/assets/membranes.py
amanzi/categories/__init__.py
amanzi/categories/category.py
amanzi/categories/consumable.py
amanzi/categories/dosing.py
amanzi/categories/energyloss.py
amanzi/categories/maintenance.py
amanzi/categories/residual.py
amanzi/components/__init__.py
amanzi/components/assistant.py
amanzi/components/connection.py
amanzi/components/projectmanager.py
amanzi/components/solution.py
amanzi/components/solvers/__init__.py
amanzi/components/solvers/categorysolver.py
amanzi/components/solvers/chemicalsolver.py
amanzi/components/solvers/masssolver.py
amanzi/core/__init__.py
amanzi/core/project.py
amanzi/core/scenario.py
amanzi/core/solver.py
amanzi/models/__init__.py
amanzi/models/cascade.py
amanzi/models/dosing.py
amanzi/models/groundwater.py
amanzi/models/ionexchange.py
amanzi/models/membrane.py
amanzi/models/membranedegassing.py
amanzi/models/model.py
amanzi/models/output.py
amanzi/models/plate.py
amanzi/models/recycle.py
amanzi/models/reservoir.py
amanzi/models/sandfiltration.py
amanzi/models/softening.py
amanzi/models/splitter.py
amanzi/models/sprayaerator.py
amanzi/models/toweraeration.py
amanzi/models/toweraerator.py
amanzi/models/vacuum.py
amanzi/models/waste.py
amanzi/models/submodels/__init__.py
amanzi/models/submodels/balance.py
amanzi/models/submodels/loss.py
amanzi/models/submodels/splitter.py
amanzi/models/tower/__init__.py
amanzi/models/tower/air_properties.py
amanzi/models/tower/compounds.py
amanzi/models/tower/engelstichlmair.py
amanzi/models/tower/mackoviak.py
amanzi/models/tower/onda.py
amanzi/models/tower/packing_properties.py
amanzi/models/tower/water_properties.py